rdmulti/__init__.py
rdmulti/rdmc.py
rdmulti/rdmcplot.py
rdmulti/rdms.py
rdmulti-1.0.1.dist-info/METADATA
rdmulti-1.0.1.dist-info/WHEEL
rdmulti-1.0.1.dist-info/top_level.txt
rdmulti-1.0.1.dist-info/RECORD
