Metadata-Version: 2.1
Name: rdmulti
Version: 1.0.1
Summary: Analysis of RD Designs with multiple cutoffs or scores
Home-page: https://github.com/rdpackages/rdmulti
Author: Ricardo Masini
Author-email: rmasini@ucdavis.edu
Project-URL: Bug Tracker, https://github.com/rdpackages/rdmulti/issues
Classifier: Programming Language :: Python :: 3
Classifier: License :: OSI Approved :: MIT License
Classifier: Operating System :: OS Independent
Requires-Python: >=3.6
Requires-Dist: numpy
Requires-Dist: pandas >=2.0.0
Requires-Dist: scipy
Requires-Dist: rdrobust >=1.1.1
